setup.py
zhr/handsome/__init__.py
zhr/handsome/boy/__init__.py
zhr/handsome/boy/message.py
zhr/zhr_zzj.egg-info/PKG-INFO
zhr/zhr_zzj.egg-info/SOURCES.txt
zhr/zhr_zzj.egg-info/dependency_links.txt
zhr/zhr_zzj.egg-info/top_level.txt