Metadata-Version: 2.1
Name: zhr-zzj
Version: 0.1
Summary: 朱活润，曾紫君
Author: zhr
License: UNKNOWN
Platform: UNKNOWN
